traffic_qtgui/__init__.py
traffic_qtgui/app.py
traffic_qtgui/console.py
traffic_qtgui/icons/travel-beige.svg
traffic_qtgui/icons/travel-grey.svg
traffic_qtgui/icons/travel-orange.svg
traffic_qtgui/icons/travel-white.svg
traffic_qtgui/icons/travel.icns
traffic_qtgui/icons/travel.ico
traffic_qtgui/layout.py
traffic_qtgui/plot.py
traffic_qtgui-1.1.dist-info/entry_points.txt
traffic_qtgui-1.1.dist-info/WHEEL
traffic_qtgui-1.1.dist-info/METADATA
traffic_qtgui-1.1.dist-info/RECORD
