Metadata-Version: 2.1
Name: traffic-qtgui
Version: 1.1
Summary: A plugin for a traffic Qt GUI
Home-page: https://github.com/traffic_viz/traffic_qtgui
License: MIT
Author: Xavier Olive
Author-email: git@xoolive.org
Requires-Python: >=3.7.1,<3.10
Classifier: License :: OSI Approved :: MIT License
Classifier: Programming Language :: Python :: 3
Classifier: Programming Language :: Python :: 3.8
Classifier: Programming Language :: Python :: 3.9
Requires-Dist: PyQt5 (>=5.15.4,<6.0.0)
Requires-Dist: pyOpenSSL (>=20.0.1,<21.0.0)
Requires-Dist: traffic (>=2.6.4,<3.0.0)
